{
	"configurations" : 
	[
		{
			"directories" : 
			[
				{
					"build" : ".",
					"childIndexes" : 
					[
						1,
						2
					],
					"hasInstallRule" : true,
					"minimumCMakeVersion" : 
					{
						"string" : "3.14"
					},
					"projectIndex" : 0,
					"source" : "."
				},
				{
					"build" : "flutter",
					"minimumCMakeVersion" : 
					{
						"string" : "3.14"
					},
					"parentIndex" : 0,
					"projectIndex" : 0,
					"source" : "flutter",
					"targetIndexes" : 
					[
						1,
						2,
						3
					]
				},
				{
					"build" : "runner",
					"minimumCMakeVersion" : 
					{
						"string" : "3.14"
					},
					"parentIndex" : 0,
					"projectIndex" : 1,
					"source" : "runner",
					"targetIndexes" : 
					[
						0
					]
				}
			],
			"name" : "Debug",
			"projects" : 
			[
				{
					"childIndexes" : 
					[
						1
					],
					"directoryIndexes" : 
					[
						0,
						1
					],
					"name" : "app",
					"targetIndexes" : 
					[
						1,
						2,
						3
					]
				},
				{
					"directoryIndexes" : 
					[
						2
					],
					"name" : "runner",
					"parentIndex" : 0,
					"targetIndexes" : 
					[
						0
					]
				}
			],
			"targets" : 
			[
				{
					"directoryIndex" : 2,
					"id" : "app::@056c4f61b0156d1d9b06",
					"jsonFile" : "target-app-Debug-8508bb7bc767919ded61.json",
					"name" : "app",
					"projectIndex" : 1
				},
				{
					"directoryIndex" : 1,
					"id" : "flutter_assemble::@2bb09fbb03a373b2cb34",
					"jsonFile" : "target-flutter_assemble-Debug-3b7ef28582eb28f21dd4.json",
					"name" : "flutter_assemble",
					"projectIndex" : 0
				},
				{
					"directoryIndex" : 1,
					"id" : "flutter_wrapper_app::@2bb09fbb03a373b2cb34",
					"jsonFile" : "target-flutter_wrapper_app-Debug-d6a1d6730a48e8fd84c5.json",
					"name" : "flutter_wrapper_app",
					"projectIndex" : 0
				},
				{
					"directoryIndex" : 1,
					"id" : "flutter_wrapper_plugin::@2bb09fbb03a373b2cb34",
					"jsonFile" : "target-flutter_wrapper_plugin-Debug-7bd9f6c211df19ed73df.json",
					"name" : "flutter_wrapper_plugin",
					"projectIndex" : 0
				}
			]
		}
	],
	"kind" : "codemodel",
	"paths" : 
	{
		"build" : "C:/Users/johng/Desktop/Look_to_Speak-main/Look_to_Speak/build",
		"source" : "C:/Users/johng/Desktop/Look_to_Speak-main/Look_to_Speak/app/windows"
	},
	"version" : 
	{
		"major" : 2,
		"minor" : 2
	}
}
